nsarchive/__init__.py
nsarchive/assets/default_avatar.png
nsarchive/cls/archives.py
nsarchive/cls/base.py
nsarchive/cls/economy.py
nsarchive/cls/entities.py
nsarchive/cls/exceptions.py
nsarchive/cls/republic.py
nsarchive/instances/_economy.py
nsarchive/instances/_entities.py
nsarchive/instances/_republic.py
nsarchive/utils.py
nsarchive-2.0.0.dist-info/LICENSE
nsarchive-2.0.0.dist-info/METADATA
nsarchive-2.0.0.dist-info/WHEEL
nsarchive-2.0.0.dist-info/RECORD
