Metadata-Version: 2.1
Name: nsarchive
Version: 2.0.0
Summary: API-wrapper pour récupérer des données liées à Nation
License: GPL-3.0
Author: happex
Author-email: 110610727+okayhappex@users.noreply.github.com
Requires-Python: >=3.10,<4.0
Classifier: License :: OSI Approved :: GNU General Public License v3 (GPLv3)
Classifier: Programming Language :: Python :: 3
Classifier: Programming Language :: Python :: 3.10
Classifier: Programming Language :: Python :: 3.11
Classifier: Programming Language :: Python :: 3.12
Requires-Dist: pillow (>=10.4,<11.0)
Requires-Dist: supabase (>=2.9.1,<3.0.0)
